<?xml version="1.0" encoding="utf-8"?>
<arch:spatialUnit xmlns:arch="http://ochre.lib.uchicago.edu/schema/SpatialUnit/SpatialUnit.xsd" xmlns:oc="http://opencontext.org/schema/space_schema_v1.xsd" xmlns:dc="http://purl.org/dc/elements/1.1/" xmlns:gml="http://www.opengis.net/gml" UUID="3C810620-E53D-443E-388C-C4F86912D675" ownedBy="05F5B702-2967-49B1-FEAA-9B2AA0184513">
  <arch:name>
    <arch:string>Level II-V anakaya</arch:string>
  </arch:name>
  <oc:item_class>
    <oc:name>Stratum</oc:name>
    <oc:iconURI>http://opencontext.org/database/ui_images/med_oc_icons/stratum_50x50.jpg</oc:iconURI>
  </oc:item_class>
  <arch:observations>
    <arch:observation obsNumber="1">
      <oc:obs_metadata>
        <oc:source>z_17_9cd844864</oc:source>
      </oc:obs_metadata>
      <arch:notes>
        <arch:note>
          <arch:string type="xhtml">
            <div xmlns="http://www.w3.org/1999/xhtml">This project provided zooarchaeological data. Please refer to other publications and sources for additional information about the strata and other archaeological contexts associated with this site.</div>
          </arch:string>
        </arch:note>
      </arch:notes>
    </arch:observation>
  </arch:observations>
  <oc:context>
    <oc:tree id="default">
      <oc:parent href="http://opencontext.org/subjects/1_Global_Spatial">
        <oc:name>Turkey</oc:name>
        <oc:id>1_Global_Spatial</oc:id>
        <oc:level>3</oc:level>
        <oc:item_class>
          <oc:name>Region</oc:name>
          <oc:iconURI>http://opencontext.org/database/ui_images/med_oc_icons/region_30x30.jpg</oc:iconURI>
        </oc:item_class>
      </oc:parent>
      <oc:parent href="http://opencontext.org/subjects/E842F47E-9C61-48C3-0D0D-A35238304F52">
        <oc:name>Köşk Höyük</oc:name>
        <oc:id>E842F47E-9C61-48C3-0D0D-A35238304F52</oc:id>
        <oc:level>2</oc:level>
        <oc:item_class>
          <oc:name>Site</oc:name>
          <oc:iconURI>http://opencontext.org/database/ui_images/med_oc_icons/site_30x30.jpg</oc:iconURI>
        </oc:item_class>
      </oc:parent>
      <oc:parent href="http://opencontext.org/subjects/2BBB7EA9-49E8-47B9-4F11-17DB920C442C">
        <oc:name>Area E7</oc:name>
        <oc:id>2BBB7EA9-49E8-47B9-4F11-17DB920C442C</oc:id>
        <oc:level>1</oc:level>
        <oc:item_class>
          <oc:name>Area</oc:name>
          <oc:iconURI>http://opencontext.org/database/ui_images/med_oc_icons/operation_area_30x30.jpg</oc:iconURI>
        </oc:item_class>
      </oc:parent>
    </oc:tree>
  </oc:context>
  <oc:children>
    <oc:tree id="default">
      <oc:child href="http://opencontext.org/subjects/7264C4D7-B250-445F-B35B-9A37FA8D47CA">
        <oc:name>Bone 16028</oc:name>
        <oc:id>7264C4D7-B250-445F-B35B-9A37FA8D47CA</oc:id>
        <oc:item_class>
          <oc:name>Animal Bone</oc:name>
          <oc:iconURI>http://opencontext.org/database/ui_images/med_oc_icons/animal_bone_30x30.jpg</oc:iconURI>
        </oc:item_class>
        <oc:descriptor>phalanx 1</oc:descriptor>
      </oc:child>
      <oc:child href="http://opencontext.org/subjects/A4457843-AD73-4CBB-CF5F-DBB6815C2442">
        <oc:name>Bone 16029</oc:name>
        <oc:id>A4457843-AD73-4CBB-CF5F-DBB6815C2442</oc:id>
        <oc:item_class>
          <oc:name>Animal Bone</oc:name>
          <oc:iconURI>http://opencontext.org/database/ui_images/med_oc_icons/animal_bone_30x30.jpg</oc:iconURI>
        </oc:item_class>
        <oc:descriptor>phalanx 1</oc:descriptor>
      </oc:child>
      <oc:child href="http://opencontext.org/subjects/CD5894E2-C317-48DE-69DB-02F448D7E604">
        <oc:name>Bone 16030</oc:name>
        <oc:id>CD5894E2-C317-48DE-69DB-02F448D7E604</oc:id>
        <oc:item_class>
          <oc:name>Animal Bone</oc:name>
          <oc:iconURI>http://opencontext.org/database/ui_images/med_oc_icons/animal_bone_30x30.jpg</oc:iconURI>
        </oc:item_class>
        <oc:descriptor>phalanx 1</oc:descriptor>
      </oc:child>
      <oc:child href="http://opencontext.org/subjects/05F6CD2F-B471-47F9-4243-9E1EEC597CAE">
        <oc:name>Bone 16031</oc:name>
        <oc:id>05F6CD2F-B471-47F9-4243-9E1EEC597CAE</oc:id>
        <oc:item_class>
          <oc:name>Animal Bone</oc:name>
          <oc:iconURI>http://opencontext.org/database/ui_images/med_oc_icons/animal_bone_30x30.jpg</oc:iconURI>
        </oc:item_class>
        <oc:descriptor>phalanx 1</oc:descriptor>
      </oc:child>
      <oc:child href="http://opencontext.org/subjects/CF4E7E17-7B1B-4525-36FE-6DEB75175483">
        <oc:name>Bone 16032</oc:name>
        <oc:id>CF4E7E17-7B1B-4525-36FE-6DEB75175483</oc:id>
        <oc:item_class>
          <oc:name>Animal Bone</oc:name>
          <oc:iconURI>http://opencontext.org/database/ui_images/med_oc_icons/animal_bone_30x30.jpg</oc:iconURI>
        </oc:item_class>
        <oc:descriptor>phalanx 1</oc:descriptor>
      </oc:child>
      <oc:child href="http://opencontext.org/subjects/B8EB41F3-6A91-4DBB-822B-4A6CE3E6BBC4">
        <oc:name>Bone 16033</oc:name>
        <oc:id>B8EB41F3-6A91-4DBB-822B-4A6CE3E6BBC4</oc:id>
        <oc:item_class>
          <oc:name>Animal Bone</oc:name>
          <oc:iconURI>http://opencontext.org/database/ui_images/med_oc_icons/animal_bone_30x30.jpg</oc:iconURI>
        </oc:item_class>
        <oc:descriptor>phalanx 1</oc:descriptor>
      </oc:child>
      <oc:child href="http://opencontext.org/subjects/8E13B0D9-9E19-4A3A-A0A5-8B0DB58E9BB3">
        <oc:name>Bone 16034</oc:name>
        <oc:id>8E13B0D9-9E19-4A3A-A0A5-8B0DB58E9BB3</oc:id>
        <oc:item_class>
          <oc:name>Animal Bone</oc:name>
          <oc:iconURI>http://opencontext.org/database/ui_images/med_oc_icons/animal_bone_30x30.jpg</oc:iconURI>
        </oc:item_class>
        <oc:descriptor>phalanx 1</oc:descriptor>
      </oc:child>
      <oc:child href="http://opencontext.org/subjects/1CC54B31-4299-44B7-552F-78F7C66B62A9">
        <oc:name>Bone 16035</oc:name>
        <oc:id>1CC54B31-4299-44B7-552F-78F7C66B62A9</oc:id>
        <oc:item_class>
          <oc:name>Animal Bone</oc:name>
          <oc:iconURI>http://opencontext.org/database/ui_images/med_oc_icons/animal_bone_30x30.jpg</oc:iconURI>
        </oc:item_class>
        <oc:descriptor>phalanx 1</oc:descriptor>
      </oc:child>
      <oc:child href="http://opencontext.org/subjects/98163A68-0C4B-4CDC-D048-A083B2687C84">
        <oc:name>Bone 16036</oc:name>
        <oc:id>98163A68-0C4B-4CDC-D048-A083B2687C84</oc:id>
        <oc:item_class>
          <oc:name>Animal Bone</oc:name>
          <oc:iconURI>http://opencontext.org/database/ui_images/med_oc_icons/animal_bone_30x30.jpg</oc:iconURI>
        </oc:item_class>
        <oc:descriptor>phalanx 1</oc:descriptor>
      </oc:child>
      <oc:child href="http://opencontext.org/subjects/C6C2EF7D-A678-4EF4-9720-E7DF6CCC74A7">
        <oc:name>Bone 16037</oc:name>
        <oc:id>C6C2EF7D-A678-4EF4-9720-E7DF6CCC74A7</oc:id>
        <oc:item_class>
          <oc:name>Animal Bone</oc:name>
          <oc:iconURI>http://opencontext.org/database/ui_images/med_oc_icons/animal_bone_30x30.jpg</oc:iconURI>
        </oc:item_class>
        <oc:descriptor>phalanx 1</oc:descriptor>
      </oc:child>
      <oc:child href="http://opencontext.org/subjects/07C0C9BE-7F00-4619-A971-450E06408760">
        <oc:name>Bone 16038</oc:name>
        <oc:id>07C0C9BE-7F00-4619-A971-450E06408760</oc:id>
        <oc:item_class>
          <oc:name>Animal Bone</oc:name>
          <oc:iconURI>http://opencontext.org/database/ui_images/med_oc_icons/animal_bone_30x30.jpg</oc:iconURI>
        </oc:item_class>
        <oc:descriptor>phalanx 1</oc:descriptor>
      </oc:child>
      <oc:child href="http://opencontext.org/subjects/8908C7B1-C8FD-43F7-B548-60266697205D">
        <oc:name>Bone 16039</oc:name>
        <oc:id>8908C7B1-C8FD-43F7-B548-60266697205D</oc:id>
        <oc:item_class>
          <oc:name>Animal Bone</oc:name>
          <oc:iconURI>http://opencontext.org/database/ui_images/med_oc_icons/animal_bone_30x30.jpg</oc:iconURI>
        </oc:item_class>
        <oc:descriptor>phalanx 2</oc:descriptor>
      </oc:child>
      <oc:child href="http://opencontext.org/subjects/5453320F-68B8-4662-D999-4705C85737A7">
        <oc:name>Bone 16040</oc:name>
        <oc:id>5453320F-68B8-4662-D999-4705C85737A7</oc:id>
        <oc:item_class>
          <oc:name>Animal Bone</oc:name>
          <oc:iconURI>http://opencontext.org/database/ui_images/med_oc_icons/animal_bone_30x30.jpg</oc:iconURI>
        </oc:item_class>
        <oc:descriptor>metatarsus III + IV</oc:descriptor>
      </oc:child>
      <oc:child href="http://opencontext.org/subjects/8EB4A173-6917-4979-582A-35D5F4158FB6">
        <oc:name>Bone 16041</oc:name>
        <oc:id>8EB4A173-6917-4979-582A-35D5F4158FB6</oc:id>
        <oc:item_class>
          <oc:name>Animal Bone</oc:name>
          <oc:iconURI>http://opencontext.org/database/ui_images/med_oc_icons/animal_bone_30x30.jpg</oc:iconURI>
        </oc:item_class>
        <oc:descriptor>metatarsus III + IV</oc:descriptor>
      </oc:child>
      <oc:child href="http://opencontext.org/subjects/5D91EF7D-877B-4D8F-04BF-5043529AC2F8">
        <oc:name>Bone 16042</oc:name>
        <oc:id>5D91EF7D-877B-4D8F-04BF-5043529AC2F8</oc:id>
        <oc:item_class>
          <oc:name>Animal Bone</oc:name>
          <oc:iconURI>http://opencontext.org/database/ui_images/med_oc_icons/animal_bone_30x30.jpg</oc:iconURI>
        </oc:item_class>
        <oc:descriptor>tarsal central + IV</oc:descriptor>
      </oc:child>
      <oc:child href="http://opencontext.org/subjects/38359AA8-1ECF-4FD0-0196-8E8782245E44">
        <oc:name>Bone 16043</oc:name>
        <oc:id>38359AA8-1ECF-4FD0-0196-8E8782245E44</oc:id>
        <oc:item_class>
          <oc:name>Animal Bone</oc:name>
          <oc:iconURI>http://opencontext.org/database/ui_images/med_oc_icons/animal_bone_30x30.jpg</oc:iconURI>
        </oc:item_class>
        <oc:descriptor>metapodial, indeterminate</oc:descriptor>
      </oc:child>
      <oc:child href="http://opencontext.org/subjects/3F532A1C-B830-4FD1-A47D-39754F34394A">
        <oc:name>Bone 16044</oc:name>
        <oc:id>3F532A1C-B830-4FD1-A47D-39754F34394A</oc:id>
        <oc:item_class>
          <oc:name>Animal Bone</oc:name>
          <oc:iconURI>http://opencontext.org/database/ui_images/med_oc_icons/animal_bone_30x30.jpg</oc:iconURI>
        </oc:item_class>
        <oc:descriptor>metapodial, indeterminate</oc:descriptor>
      </oc:child>
      <oc:child href="http://opencontext.org/subjects/C024B370-1416-444E-9AF2-DDBB5D7AD753">
        <oc:name>Bone 16045</oc:name>
        <oc:id>C024B370-1416-444E-9AF2-DDBB5D7AD753</oc:id>
        <oc:item_class>
          <oc:name>Animal Bone</oc:name>
          <oc:iconURI>http://opencontext.org/database/ui_images/med_oc_icons/animal_bone_30x30.jpg</oc:iconURI>
        </oc:item_class>
        <oc:descriptor>radius</oc:descriptor>
      </oc:child>
      <oc:child href="http://opencontext.org/subjects/F00CB46A-1173-48B5-3D35-9D6B6D389FE7">
        <oc:name>Bone 16046</oc:name>
        <oc:id>F00CB46A-1173-48B5-3D35-9D6B6D389FE7</oc:id>
        <oc:item_class>
          <oc:name>Animal Bone</oc:name>
          <oc:iconURI>http://opencontext.org/database/ui_images/med_oc_icons/animal_bone_30x30.jpg</oc:iconURI>
        </oc:item_class>
        <oc:descriptor>radius</oc:descriptor>
      </oc:child>
      <oc:child href="http://opencontext.org/subjects/F31378CF-2913-4CC6-5012-6BF16121945B">
        <oc:name>Bone 16047</oc:name>
        <oc:id>F31378CF-2913-4CC6-5012-6BF16121945B</oc:id>
        <oc:item_class>
          <oc:name>Animal Bone</oc:name>
          <oc:iconURI>http://opencontext.org/database/ui_images/med_oc_icons/animal_bone_30x30.jpg</oc:iconURI>
        </oc:item_class>
        <oc:descriptor>radius</oc:descriptor>
      </oc:child>
      <oc:child href="http://opencontext.org/subjects/BEA60076-9F7C-479A-7325-D2E0F608D905">
        <oc:name>Bone 16048</oc:name>
        <oc:id>BEA60076-9F7C-479A-7325-D2E0F608D905</oc:id>
        <oc:item_class>
          <oc:name>Animal Bone</oc:name>
          <oc:iconURI>http://opencontext.org/database/ui_images/med_oc_icons/animal_bone_30x30.jpg</oc:iconURI>
        </oc:item_class>
        <oc:descriptor>radius</oc:descriptor>
      </oc:child>
      <oc:child href="http://opencontext.org/subjects/EAB82956-B1C2-4619-1B18-740345255940">
        <oc:name>Bone 16049</oc:name>
        <oc:id>EAB82956-B1C2-4619-1B18-740345255940</oc:id>
        <oc:item_class>
          <oc:name>Animal Bone</oc:name>
          <oc:iconURI>http://opencontext.org/database/ui_images/med_oc_icons/animal_bone_30x30.jpg</oc:iconURI>
        </oc:item_class>
        <oc:descriptor>tibia</oc:descriptor>
      </oc:child>
      <oc:child href="http://opencontext.org/subjects/F33F82CE-3FBC-4380-68CB-1FB6A6F7FA81">
        <oc:name>Bone 16050</oc:name>
        <oc:id>F33F82CE-3FBC-4380-68CB-1FB6A6F7FA81</oc:id>
        <oc:item_class>
          <oc:name>Animal Bone</oc:name>
          <oc:iconURI>http://opencontext.org/database/ui_images/med_oc_icons/animal_bone_30x30.jpg</oc:iconURI>
        </oc:item_class>
        <oc:descriptor>tibia</oc:descriptor>
      </oc:child>
      <oc:child href="http://opencontext.org/subjects/71B8274C-8B3F-460D-54D4-19FBF09E71C5">
        <oc:name>Bone 16051</oc:name>
        <oc:id>71B8274C-8B3F-460D-54D4-19FBF09E71C5</oc:id>
        <oc:item_class>
          <oc:name>Animal Bone</oc:name>
          <oc:iconURI>http://opencontext.org/database/ui_images/med_oc_icons/animal_bone_30x30.jpg</oc:iconURI>
        </oc:item_class>
        <oc:descriptor>astragalus</oc:descriptor>
      </oc:child>
      <oc:child href="http://opencontext.org/subjects/BAF30213-0DE7-44E8-B24E-31D069B2352B">
        <oc:name>Bone 16052</oc:name>
        <oc:id>BAF30213-0DE7-44E8-B24E-31D069B2352B</oc:id>
        <oc:item_class>
          <oc:name>Animal Bone</oc:name>
          <oc:iconURI>http://opencontext.org/database/ui_images/med_oc_icons/animal_bone_30x30.jpg</oc:iconURI>
        </oc:item_class>
        <oc:descriptor>femur</oc:descriptor>
      </oc:child>
      <oc:child href="http://opencontext.org/subjects/3C808FFE-6669-4CFB-26B7-833EA8EA5399">
        <oc:name>Bone 16053</oc:name>
        <oc:id>3C808FFE-6669-4CFB-26B7-833EA8EA5399</oc:id>
        <oc:item_class>
          <oc:name>Animal Bone</oc:name>
          <oc:iconURI>http://opencontext.org/database/ui_images/med_oc_icons/animal_bone_30x30.jpg</oc:iconURI>
        </oc:item_class>
        <oc:descriptor>loose tooth</oc:descriptor>
      </oc:child>
      <oc:child href="http://opencontext.org/subjects/B8FEF862-70D1-4367-20A0-3990D2B7D8F5">
        <oc:name>Bone 16054</oc:name>
        <oc:id>B8FEF862-70D1-4367-20A0-3990D2B7D8F5</oc:id>
        <oc:item_class>
          <oc:name>Animal Bone</oc:name>
          <oc:iconURI>http://opencontext.org/database/ui_images/med_oc_icons/animal_bone_30x30.jpg</oc:iconURI>
        </oc:item_class>
        <oc:descriptor>loose tooth</oc:descriptor>
      </oc:child>
      <oc:child href="http://opencontext.org/subjects/7A20387E-279B-4C89-017A-968D098E1C08">
        <oc:name>Bone 16055</oc:name>
        <oc:id>7A20387E-279B-4C89-017A-968D098E1C08</oc:id>
        <oc:item_class>
          <oc:name>Animal Bone</oc:name>
          <oc:iconURI>http://opencontext.org/database/ui_images/med_oc_icons/animal_bone_30x30.jpg</oc:iconURI>
        </oc:item_class>
        <oc:descriptor>loose tooth</oc:descriptor>
      </oc:child>
      <oc:child href="http://opencontext.org/subjects/E4CD42A7-1CFF-47E6-E4B9-93C989B52535">
        <oc:name>Bone 16056</oc:name>
        <oc:id>E4CD42A7-1CFF-47E6-E4B9-93C989B52535</oc:id>
        <oc:item_class>
          <oc:name>Animal Bone</oc:name>
          <oc:iconURI>http://opencontext.org/database/ui_images/med_oc_icons/animal_bone_30x30.jpg</oc:iconURI>
        </oc:item_class>
        <oc:descriptor>loose tooth</oc:descriptor>
      </oc:child>
      <oc:child href="http://opencontext.org/subjects/CF922461-65ED-450E-E19D-626B4DD31DBA">
        <oc:name>Bone 16057</oc:name>
        <oc:id>CF922461-65ED-450E-E19D-626B4DD31DBA</oc:id>
        <oc:item_class>
          <oc:name>Animal Bone</oc:name>
          <oc:iconURI>http://opencontext.org/database/ui_images/med_oc_icons/animal_bone_30x30.jpg</oc:iconURI>
        </oc:item_class>
        <oc:descriptor>loose tooth</oc:descriptor>
      </oc:child>
      <oc:child href="http://opencontext.org/subjects/F5A8DF90-94C1-4841-2005-69C2E3424859">
        <oc:name>Bone 16058</oc:name>
        <oc:id>F5A8DF90-94C1-4841-2005-69C2E3424859</oc:id>
        <oc:item_class>
          <oc:name>Animal Bone</oc:name>
          <oc:iconURI>http://opencontext.org/database/ui_images/med_oc_icons/animal_bone_30x30.jpg</oc:iconURI>
        </oc:item_class>
        <oc:descriptor>loose tooth</oc:descriptor>
      </oc:child>
      <oc:child href="http://opencontext.org/subjects/6237DD98-020E-4DE2-6A3E-8A07C00767FF">
        <oc:name>Bone 16059</oc:name>
        <oc:id>6237DD98-020E-4DE2-6A3E-8A07C00767FF</oc:id>
        <oc:item_class>
          <oc:name>Animal Bone</oc:name>
          <oc:iconURI>http://opencontext.org/database/ui_images/med_oc_icons/animal_bone_30x30.jpg</oc:iconURI>
        </oc:item_class>
        <oc:descriptor>loose tooth</oc:descriptor>
      </oc:child>
      <oc:child href="http://opencontext.org/subjects/C3DFF45A-135A-4FAE-C42C-58EC65C0CB7A">
        <oc:name>Bone 16060</oc:name>
        <oc:id>C3DFF45A-135A-4FAE-C42C-58EC65C0CB7A</oc:id>
        <oc:item_class>
          <oc:name>Animal Bone</oc:name>
          <oc:iconURI>http://opencontext.org/database/ui_images/med_oc_icons/animal_bone_30x30.jpg</oc:iconURI>
        </oc:item_class>
        <oc:descriptor>loose tooth</oc:descriptor>
      </oc:child>
      <oc:child href="http://opencontext.org/subjects/A2DF2A84-AE59-4A2B-31C4-2416901066E3">
        <oc:name>Bone 16061</oc:name>
        <oc:id>A2DF2A84-AE59-4A2B-31C4-2416901066E3</oc:id>
        <oc:item_class>
          <oc:name>Animal Bone</oc:name>
          <oc:iconURI>http://opencontext.org/database/ui_images/med_oc_icons/animal_bone_30x30.jpg</oc:iconURI>
        </oc:item_class>
        <oc:descriptor>loose tooth</oc:descriptor>
      </oc:child>
      <oc:child href="http://opencontext.org/subjects/6110F0FC-55DE-457B-B6B9-33C9ADCDF18B">
        <oc:name>Bone 16062</oc:name>
        <oc:id>6110F0FC-55DE-457B-B6B9-33C9ADCDF18B</oc:id>
        <oc:item_class>
          <oc:name>Animal Bone</oc:name>
          <oc:iconURI>http://opencontext.org/database/ui_images/med_oc_icons/animal_bone_30x30.jpg</oc:iconURI>
        </oc:item_class>
        <oc:descriptor>loose tooth</oc:descriptor>
      </oc:child>
      <oc:child href="http://opencontext.org/subjects/C6D84901-C6D1-4287-131D-19C93FF33553">
        <oc:name>Bone 16063</oc:name>
        <oc:id>C6D84901-C6D1-4287-131D-19C93FF33553</oc:id>
        <oc:item_class>
          <oc:name>Animal Bone</oc:name>
          <oc:iconURI>http://opencontext.org/database/ui_images/med_oc_icons/animal_bone_30x30.jpg</oc:iconURI>
        </oc:item_class>
        <oc:descriptor>loose tooth</oc:descriptor>
      </oc:child>
      <oc:child href="http://opencontext.org/subjects/F8163CD5-F298-4DE7-7C9C-5BEE051EED59">
        <oc:name>Bone 16064</oc:name>
        <oc:id>F8163CD5-F298-4DE7-7C9C-5BEE051EED59</oc:id>
        <oc:item_class>
          <oc:name>Animal Bone</oc:name>
          <oc:iconURI>http://opencontext.org/database/ui_images/med_oc_icons/animal_bone_30x30.jpg</oc:iconURI>
        </oc:item_class>
        <oc:descriptor>scapula</oc:descriptor>
      </oc:child>
      <oc:child href="http://opencontext.org/subjects/D8B227C7-296A-432F-0D23-F9276E6D3C09">
        <oc:name>Bone 16065</oc:name>
        <oc:id>D8B227C7-296A-432F-0D23-F9276E6D3C09</oc:id>
        <oc:item_class>
          <oc:name>Animal Bone</oc:name>
          <oc:iconURI>http://opencontext.org/database/ui_images/med_oc_icons/animal_bone_30x30.jpg</oc:iconURI>
        </oc:item_class>
        <oc:descriptor>tibia</oc:descriptor>
      </oc:child>
      <oc:child href="http://opencontext.org/subjects/C9E9DD8A-8350-45AE-9B81-1E4C457DB86C">
        <oc:name>Bone 16066</oc:name>
        <oc:id>C9E9DD8A-8350-45AE-9B81-1E4C457DB86C</oc:id>
        <oc:item_class>
          <oc:name>Animal Bone</oc:name>
          <oc:iconURI>http://opencontext.org/database/ui_images/med_oc_icons/animal_bone_30x30.jpg</oc:iconURI>
        </oc:item_class>
        <oc:descriptor>tibia</oc:descriptor>
      </oc:child>
      <oc:child href="http://opencontext.org/subjects/1D1838F3-85AF-427F-2F47-0E5FF1A06B4E">
        <oc:name>Bone 16067</oc:name>
        <oc:id>1D1838F3-85AF-427F-2F47-0E5FF1A06B4E</oc:id>
        <oc:item_class>
          <oc:name>Animal Bone</oc:name>
          <oc:iconURI>http://opencontext.org/database/ui_images/med_oc_icons/animal_bone_30x30.jpg</oc:iconURI>
        </oc:item_class>
        <oc:descriptor>scapula</oc:descriptor>
      </oc:child>
      <oc:child href="http://opencontext.org/subjects/85AB312B-0EE3-43A6-73E4-70E1D8A72D9C">
        <oc:name>Bone 16068</oc:name>
        <oc:id>85AB312B-0EE3-43A6-73E4-70E1D8A72D9C</oc:id>
        <oc:item_class>
          <oc:name>Animal Bone</oc:name>
          <oc:iconURI>http://opencontext.org/database/ui_images/med_oc_icons/animal_bone_30x30.jpg</oc:iconURI>
        </oc:item_class>
        <oc:descriptor>metacarpus III + IV</oc:descriptor>
      </oc:child>
      <oc:child href="http://opencontext.org/subjects/4733B87F-8A4E-4B24-A7E6-E63A4131DD2D">
        <oc:name>Bone 16069</oc:name>
        <oc:id>4733B87F-8A4E-4B24-A7E6-E63A4131DD2D</oc:id>
        <oc:item_class>
          <oc:name>Animal Bone</oc:name>
          <oc:iconURI>http://opencontext.org/database/ui_images/med_oc_icons/animal_bone_30x30.jpg</oc:iconURI>
        </oc:item_class>
        <oc:descriptor>metacarpus III + IV</oc:descriptor>
      </oc:child>
      <oc:child href="http://opencontext.org/subjects/26C12BEF-674E-456E-2718-B7214FABFEF2">
        <oc:name>Bone 16070</oc:name>
        <oc:id>26C12BEF-674E-456E-2718-B7214FABFEF2</oc:id>
        <oc:item_class>
          <oc:name>Animal Bone</oc:name>
          <oc:iconURI>http://opencontext.org/database/ui_images/med_oc_icons/animal_bone_30x30.jpg</oc:iconURI>
        </oc:item_class>
        <oc:descriptor>humerus</oc:descriptor>
      </oc:child>
      <oc:child href="http://opencontext.org/subjects/F108DADD-07F6-4D57-4AE1-6B8466FE708F">
        <oc:name>Bone 16071</oc:name>
        <oc:id>F108DADD-07F6-4D57-4AE1-6B8466FE708F</oc:id>
        <oc:item_class>
          <oc:name>Animal Bone</oc:name>
          <oc:iconURI>http://opencontext.org/database/ui_images/med_oc_icons/animal_bone_30x30.jpg</oc:iconURI>
        </oc:item_class>
        <oc:descriptor>metacarpus III + IV</oc:descriptor>
      </oc:child>
      <oc:child href="http://opencontext.org/subjects/1C90430D-A081-47DC-332E-8F480F7B0511">
        <oc:name>Bone 16072</oc:name>
        <oc:id>1C90430D-A081-47DC-332E-8F480F7B0511</oc:id>
        <oc:item_class>
          <oc:name>Animal Bone</oc:name>
          <oc:iconURI>http://opencontext.org/database/ui_images/med_oc_icons/animal_bone_30x30.jpg</oc:iconURI>
        </oc:item_class>
        <oc:descriptor>metacarpus III + IV</oc:descriptor>
      </oc:child>
      <oc:child href="http://opencontext.org/subjects/82365032-ACB6-42C4-60B6-18A2E763913F">
        <oc:name>Bone 16073</oc:name>
        <oc:id>82365032-ACB6-42C4-60B6-18A2E763913F</oc:id>
        <oc:item_class>
          <oc:name>Animal Bone</oc:name>
          <oc:iconURI>http://opencontext.org/database/ui_images/med_oc_icons/animal_bone_30x30.jpg</oc:iconURI>
        </oc:item_class>
        <oc:descriptor>metacarpus III + IV</oc:descriptor>
      </oc:child>
      <oc:child href="http://opencontext.org/subjects/4EA983B0-ECEA-48DC-EE58-DBFE81F80C07">
        <oc:name>Bone 16074</oc:name>
        <oc:id>4EA983B0-ECEA-48DC-EE58-DBFE81F80C07</oc:id>
        <oc:item_class>
          <oc:name>Animal Bone</oc:name>
          <oc:iconURI>http://opencontext.org/database/ui_images/med_oc_icons/animal_bone_30x30.jpg</oc:iconURI>
        </oc:item_class>
        <oc:descriptor>metacarpus III + IV</oc:descriptor>
      </oc:child>
      <oc:child href="http://opencontext.org/subjects/E37E6DC0-A88F-48E2-1C09-D8597415FE28">
        <oc:name>Bone 16075</oc:name>
        <oc:id>E37E6DC0-A88F-48E2-1C09-D8597415FE28</oc:id>
        <oc:item_class>
          <oc:name>Animal Bone</oc:name>
          <oc:iconURI>http://opencontext.org/database/ui_images/med_oc_icons/animal_bone_30x30.jpg</oc:iconURI>
        </oc:item_class>
        <oc:descriptor>metacarpus III + IV</oc:descriptor>
      </oc:child>
      <oc:child href="http://opencontext.org/subjects/CC394EFA-03FB-48FB-0E04-2A3F587BF5D3">
        <oc:name>Bone 16076</oc:name>
        <oc:id>CC394EFA-03FB-48FB-0E04-2A3F587BF5D3</oc:id>
        <oc:item_class>
          <oc:name>Animal Bone</oc:name>
          <oc:iconURI>http://opencontext.org/database/ui_images/med_oc_icons/animal_bone_30x30.jpg</oc:iconURI>
        </oc:item_class>
        <oc:descriptor>metacarpus III + IV</oc:descriptor>
      </oc:child>
      <oc:child href="http://opencontext.org/subjects/4E4DB43D-D186-49FE-1CCB-4467567A0E6A">
        <oc:name>Bone 16077</oc:name>
        <oc:id>4E4DB43D-D186-49FE-1CCB-4467567A0E6A</oc:id>
        <oc:item_class>
          <oc:name>Animal Bone</oc:name>
          <oc:iconURI>http://opencontext.org/database/ui_images/med_oc_icons/animal_bone_30x30.jpg</oc:iconURI>
        </oc:item_class>
        <oc:descriptor>mandible with teeth</oc:descriptor>
      </oc:child>
      <oc:child href="http://opencontext.org/subjects/E53DD2BE-FD7C-485E-A64C-95EC6E1F1B8A">
        <oc:name>Bone 16078</oc:name>
        <oc:id>E53DD2BE-FD7C-485E-A64C-95EC6E1F1B8A</oc:id>
        <oc:item_class>
          <oc:name>Animal Bone</oc:name>
          <oc:iconURI>http://opencontext.org/database/ui_images/med_oc_icons/animal_bone_30x30.jpg</oc:iconURI>
        </oc:item_class>
        <oc:descriptor>mandible with teeth</oc:descriptor>
      </oc:child>
      <oc:child href="http://opencontext.org/subjects/DCA27160-4083-484A-DD07-3C1ED3E7E95C">
        <oc:name>Bone 16079</oc:name>
        <oc:id>DCA27160-4083-484A-DD07-3C1ED3E7E95C</oc:id>
        <oc:item_class>
          <oc:name>Animal Bone</oc:name>
          <oc:iconURI>http://opencontext.org/database/ui_images/med_oc_icons/animal_bone_30x30.jpg</oc:iconURI>
        </oc:item_class>
        <oc:descriptor>mandible with teeth</oc:descriptor>
      </oc:child>
      <oc:child href="http://opencontext.org/subjects/4C9B71E5-3B56-457F-201F-70910A9A8CEB">
        <oc:name>Bone 16080</oc:name>
        <oc:id>4C9B71E5-3B56-457F-201F-70910A9A8CEB</oc:id>
        <oc:item_class>
          <oc:name>Animal Bone</oc:name>
          <oc:iconURI>http://opencontext.org/database/ui_images/med_oc_icons/animal_bone_30x30.jpg</oc:iconURI>
        </oc:item_class>
        <oc:descriptor>mandible with teeth</oc:descriptor>
      </oc:child>
      <oc:child href="http://opencontext.org/subjects/0A567335-8FF6-4AB6-55B1-257FCC45BD8A">
        <oc:name>Bone 16081</oc:name>
        <oc:id>0A567335-8FF6-4AB6-55B1-257FCC45BD8A</oc:id>
        <oc:item_class>
          <oc:name>Animal Bone</oc:name>
          <oc:iconURI>http://opencontext.org/database/ui_images/med_oc_icons/animal_bone_30x30.jpg</oc:iconURI>
        </oc:item_class>
        <oc:descriptor>mandible with teeth</oc:descriptor>
      </oc:child>
      <oc:child href="http://opencontext.org/subjects/C3EB2436-BDC0-4A68-4C6A-B6D8464CF597">
        <oc:name>Bone 16082</oc:name>
        <oc:id>C3EB2436-BDC0-4A68-4C6A-B6D8464CF597</oc:id>
        <oc:item_class>
          <oc:name>Animal Bone</oc:name>
          <oc:iconURI>http://opencontext.org/database/ui_images/med_oc_icons/animal_bone_30x30.jpg</oc:iconURI>
        </oc:item_class>
        <oc:descriptor>loose tooth</oc:descriptor>
      </oc:child>
      <oc:child href="http://opencontext.org/subjects/F37BB8BA-EC0C-4A29-8D89-B97ED94A88CF">
        <oc:name>Bone 16083</oc:name>
        <oc:id>F37BB8BA-EC0C-4A29-8D89-B97ED94A88CF</oc:id>
        <oc:item_class>
          <oc:name>Animal Bone</oc:name>
          <oc:iconURI>http://opencontext.org/database/ui_images/med_oc_icons/animal_bone_30x30.jpg</oc:iconURI>
        </oc:item_class>
        <oc:descriptor>loose tooth</oc:descriptor>
      </oc:child>
      <oc:child href="http://opencontext.org/subjects/2391008E-F5FA-4E34-E0B4-D56FAD5E3826">
        <oc:name>Bone 16084</oc:name>
        <oc:id>2391008E-F5FA-4E34-E0B4-D56FAD5E3826</oc:id>
        <oc:item_class>
          <oc:name>Animal Bone</oc:name>
          <oc:iconURI>http://opencontext.org/database/ui_images/med_oc_icons/animal_bone_30x30.jpg</oc:iconURI>
        </oc:item_class>
        <oc:descriptor>loose tooth</oc:descriptor>
      </oc:child>
      <oc:child href="http://opencontext.org/subjects/0310802D-191E-4A49-6D8B-00352D452347">
        <oc:name>Bone 16085</oc:name>
        <oc:id>0310802D-191E-4A49-6D8B-00352D452347</oc:id>
        <oc:item_class>
          <oc:name>Animal Bone</oc:name>
          <oc:iconURI>http://opencontext.org/database/ui_images/med_oc_icons/animal_bone_30x30.jpg</oc:iconURI>
        </oc:item_class>
        <oc:descriptor>loose tooth</oc:descriptor>
      </oc:child>
    </oc:tree>
  </oc:children>
  <oc:metadata>
    <dc:title>Köşk Höyük Faunal Data: Level II-V anakaya (Stratum)</dc:title>
    <dc:publisher>Open Context</dc:publisher>
    <dc:date>2013-05-17</dc:date>
    <dc:subject>Turkey</dc:subject>
    <dc:subject>Zooarchaeology</dc:subject>
    <dc:subject>Pastoralism</dc:subject>
    <dc:subject>Faunal data, Mammal Remains, Chalcolithic, Village, Central Anatolia</dc:subject>
    <dc:subject>Köşk Höyük</dc:subject>
    <dc:subject>Equids</dc:subject>
    <dc:subject>Animal Economy</dc:subject>
    <dc:creator href="http://opencontext.org/persons/2C4A531B-250C-4420-DA62-3C8CFD23F926">Benjamin S. Arbuckle</dc:creator>
    <dc:identifier>http://opencontext.org/subjects/3C810620-E53D-443E-388C-C4F86912D675</dc:identifier>
    <oc:project_name href="http://opencontext.org/projects/05F5B702-2967-49B1-FEAA-9B2AA0184513">Köşk Höyük Faunal Data</oc:project_name>
    <oc:pub_date>2013-05-17T00:00:00-07:00</oc:pub_date>
    <oc:coins>ctx_ver=Z39.88-2004&amp;rft_val_fmt=info%3Aofi%2Ffmt%3Akev%3Amtx%3Adc&amp;rft_val_fmt=info%3Aofi%2Ffmt%3Akev%3Amtx%3Adc&amp;rft.type=dataset&amp;rft.title=K%C3%B6%C5%9Fk+H%C3%B6y%C3%BCk+Faunal+Data%3A+Level+II-V+anakaya+%28Stratum%29&amp;rft.publisher=Open+Context&amp;rft.source=Open+Context&amp;rft.subject=Turkey&amp;rft.subject=Zooarchaeology&amp;rft.subject=Pastoralism&amp;rft.subject=Faunal+data%2C+Mammal+Remains%2C+Chalcolithic%2C+Village%2C+Central+Anatolia&amp;rft.subject=K%C3%B6%C5%9Fk+H%C3%B6y%C3%BCk&amp;rft.subject=Equids&amp;rft.subject=Animal+Economy&amp;rft.creator=Benjamin+S.+Arbuckle&amp;rft.identifier=http%3A%2F%2Fopencontext.org%2Fsubjects%2F3C810620-E53D-443E-388C-C4F86912D675</oc:coins>
    <oc:geo_reference>
      <oc:geo_lat>37.84779</oc:geo_lat>
      <oc:geo_long>34.611821</oc:geo_long>
      <oc:metasource ref_type="contained" href="http://opencontext.org/subjects/E842F47E-9C61-48C3-0D0D-A35238304F52">
        <oc:source_name>Köşk Höyük</oc:source_name>
        <oc:source_id>E842F47E-9C61-48C3-0D0D-A35238304F52</oc:source_id>
      </oc:metasource>
    </oc:geo_reference>
    <oc:copyright_lic href="http://creativecommons.org/licenses/by/3.0/">
      <oc:lic_name>Attribution</oc:lic_name>
      <oc:lic_vers>3</oc:lic_vers>
      <oc:lic_URI>http://creativecommons.org/licenses/by/3.0/</oc:lic_URI>
      <oc:lic_icon_URI>http://i.creativecommons.org/l/by/3.0/88x31.png</oc:lic_icon_URI>
    </oc:copyright_lic>
  </oc:metadata>
  <oc:social_usage>
    <oc:last_updated>2013-05-18T17:24:54-07:00</oc:last_updated>
    <oc:item_views>
      <oc:count>1</oc:count>
      <oc:view_time>2013/05/18 17:24:54</oc:view_time>
    </oc:item_views>
    <oc:user_tags>
      <oc:tag type="chronological" status="public">
        <oc:name>(6,200 BCE - 5,500 BCE)</oc:name>
        <oc:chrono isDuration="true">
          <oc:time_start>-6200</oc:time_start>
          <oc:time_finish>-5500</oc:time_finish>
          <oc:metasource ref_type="contained" href="http://opencontext.org/subjects/E842F47E-9C61-48C3-0D0D-A35238304F52">
            <oc:source_name>Köşk Höyük</oc:source_name>
            <oc:source_id>E842F47E-9C61-48C3-0D0D-A35238304F52</oc:source_id>
          </oc:metasource>
        </oc:chrono>
        <oc:tag_creator id="oc">
          <oc:creator_name>Open Context Editors</oc:creator_name>
          <oc:set_label>Default set</oc:set_label>
          <oc:set_id>Default set</oc:set_id>
          <oc:set_date>2013-02-28T17:35:06-07:00</oc:set_date>
        </oc:tag_creator>
      </oc:tag>
    </oc:user_tags>
  </oc:social_usage>
</arch:spatialUnit>
